mitchallen/__init__.py
mitchallen/roll/__init__.py
mitchallen_roll-1.0.14.dist-info/METADATA
mitchallen_roll-1.0.14.dist-info/WHEEL
mitchallen_roll-1.0.14.dist-info/licenses/LICENSE
mitchallen_roll-1.0.14.dist-info/RECORD
