Metadata-Version: 2.4
Name: mitchallen-roll
Version: 1.0.14
Summary: A simple, lightweight Python package for dice rolling simulations with customizable sides, perfect for games, RPGs, and probabilistic applications
Project-URL: Homepage, https://github.com/mitchallen/python-coin-flip
Project-URL: Repository, https://github.com/mitchallen/python-coin-flip
Project-URL: Issues, https://github.com/mitchallen/python-coin-flip/issues
Author: Mitch Allen
License: MIT
License-File: LICENSE
Keywords: dice,generator,random,random-number,roll
Classifier: Development Status :: 4 - Beta
Classifier: Intended Audience :: Developers
Classifier: License :: OSI Approved :: MIT License
Classifier: Programming Language :: Python :: 3
Classifier: Programming Language :: Python :: 3.12
Classifier: Programming Language :: Python :: 3.13
Classifier: Topic :: Software Development :: Libraries :: Python Modules
Classifier: Topic :: Utilities
Requires-Python: >=3.12
